{
  "url": "https://api.github.com/repos/tensorflow/tensorflow/issues/32144",
  "repository_url": "https://api.github.com/repos/tensorflow/tensorflow",
  "labels_url": "https://api.github.com/repos/tensorflow/tensorflow/issues/32144/labels{/name}",
  "comments_url": "https://api.github.com/repos/tensorflow/tensorflow/issues/32144/comments",
  "events_url": "https://api.github.com/repos/tensorflow/tensorflow/issues/32144/events",
  "html_url": "https://github.com/tensorflow/tensorflow/issues/32144",
  "id": 487934847,
  "node_id": "MDU6SXNzdWU0ODc5MzQ4NDc=",
  "number": 32144,
  "title": "TF 2.0: metrics get mixed up when adding metrics in multiple layers",
  "user": {
    "login": "peterkfm",
    "id": 21103431,
    "node_id": "MDQ6VXNlcjIxMTAzNDMx",
    "avatar_url": "https://avatars.githubusercontent.com/u/21103431?v=4",
    "gravatar_id": "",
    "url": "https://api.github.com/users/peterkfm",
    "html_url": "https://github.com/peterkfm",
    "followers_url": "https://api.github.com/users/peterkfm/followers",
    "following_url": "https://api.github.com/users/peterkfm/following{/other_user}",
    "gists_url": "https://api.github.com/users/peterkfm/gists{/gist_id}",
    "starred_url": "https://api.github.com/users/peterkfm/starred{/owner}{/repo}",
    "subscriptions_url": "https://api.github.com/users/peterkfm/subscriptions",
    "organizations_url": "https://api.github.com/users/peterkfm/orgs",
    "repos_url": "https://api.github.com/users/peterkfm/repos",
    "events_url": "https://api.github.com/users/peterkfm/events{/privacy}",
    "received_events_url": "https://api.github.com/users/peterkfm/received_events",
    "type": "User",
    "site_admin": false
  },
  "labels": [
    {
      "id": 404586594,
      "node_id": "MDU6TGFiZWw0MDQ1ODY1OTQ=",
      "url": "https://api.github.com/repos/tensorflow/tensorflow/labels/stat:awaiting%20tensorflower",
      "name": "stat:awaiting tensorflower",
      "color": "f4b400",
      "default": false,
      "description": "Status  - Awaiting response from tensorflower"
    },
    {
      "id": 473172988,
      "node_id": "MDU6TGFiZWw0NzMxNzI5ODg=",
      "url": "https://api.github.com/repos/tensorflow/tensorflow/labels/type:bug",
      "name": "type:bug",
      "color": "159b2e",
      "default": false,
      "description": "Bug"
    },
    {
      "id": 1097546578,
      "node_id": "MDU6TGFiZWwxMDk3NTQ2NTc4",
      "url": "https://api.github.com/repos/tensorflow/tensorflow/labels/comp:keras",
      "name": "comp:keras",
      "color": "0052cc",
      "default": false,
      "description": "Keras related issues"
    },
    {
      "id": 1160540362,
      "node_id": "MDU6TGFiZWwxMTYwNTQwMzYy",
      "url": "https://api.github.com/repos/tensorflow/tensorflow/labels/TF%202.0",
      "name": "TF 2.0",
      "color": "e79b38",
      "default": false,
      "description": "Issues relating to TensorFlow 2.0"
    }
  ],
  "state": "closed",
  "locked": false,
  "assignee": {
    "login": "pavithrasv",
    "id": 13326758,
    "node_id": "MDQ6VXNlcjEzMzI2NzU4",
    "avatar_url": "https://avatars.githubusercontent.com/u/13326758?v=4",
    "gravatar_id": "",
    "url": "https://api.github.com/users/pavithrasv",
    "html_url": "https://github.com/pavithrasv",
    "followers_url": "https://api.github.com/users/pavithrasv/followers",
    "following_url": "https://api.github.com/users/pavithrasv/following{/other_user}",
    "gists_url": "https://api.github.com/users/pavithrasv/gists{/gist_id}",
    "starred_url": "https://api.github.com/users/pavithrasv/starred{/owner}{/repo}",
    "subscriptions_url": "https://api.github.com/users/pavithrasv/subscriptions",
    "organizations_url": "https://api.github.com/users/pavithrasv/orgs",
    "repos_url": "https://api.github.com/users/pavithrasv/repos",
    "events_url": "https://api.github.com/users/pavithrasv/events{/privacy}",
    "received_events_url": "https://api.github.com/users/pavithrasv/received_events",
    "type": "User",
    "site_admin": false
  },
  "assignees": [
    {
      "login": "pavithrasv",
      "id": 13326758,
      "node_id": "MDQ6VXNlcjEzMzI2NzU4",
      "avatar_url": "https://avatars.githubusercontent.com/u/13326758?v=4",
      "gravatar_id": "",
      "url": "https://api.github.com/users/pavithrasv",
      "html_url": "https://github.com/pavithrasv",
      "followers_url": "https://api.github.com/users/pavithrasv/followers",
      "following_url": "https://api.github.com/users/pavithrasv/following{/other_user}",
      "gists_url": "https://api.github.com/users/pavithrasv/gists{/gist_id}",
      "starred_url": "https://api.github.com/users/pavithrasv/starred{/owner}{/repo}",
      "subscriptions_url": "https://api.github.com/users/pavithrasv/subscriptions",
      "organizations_url": "https://api.github.com/users/pavithrasv/orgs",
      "repos_url": "https://api.github.com/users/pavithrasv/repos",
      "events_url": "https://api.github.com/users/pavithrasv/events{/privacy}",
      "received_events_url": "https://api.github.com/users/pavithrasv/received_events",
      "type": "User",
      "site_admin": false
    }
  ],
  "milestone": null,
  "comments": 3,
  "created_at": "2019-09-01T21:52:56Z",
  "updated_at": "2020-04-29T23:24:15Z",
  "closed_at": "2019-09-05T19:50:05Z",
  "author_association": "NONE",
  "active_lock_reason": null,
  "body": "**System information**\r\n- Have I written custom code (as opposed to using a stock example script provided in TensorFlow): Yes\r\n- OS Platform and Distribution (e.g., Linux Ubuntu 16.04): macOS 10.14.6, Ubuntu 18.04\r\n- TensorFlow installed from (source or binary): binary\r\n- TensorFlow version (use command below): v2.0.0-beta0-16-g1d91213fe7 2.0.0-beta1 and v2.0.0-beta1-5101-gc75bb66a99 2.0.0-rc0\r\n- Python version: 3.6.6\r\n- CUDA/cuDNN version: N/A\r\n- GPU model and memory: N/A\r\n\r\n**Describe the current behavior**\r\nCreating a Layer and Model, calling `add_metric` in both results in the metric values getting mixed up.\r\n\r\n**Describe the expected behavior**\r\nMetric values should not get mixed up\r\n\r\n**Code to reproduce the issue**\r\n```python\r\n#!/usr/bin/env python\r\n\r\nimport numpy as np\r\nimport tensorflow as tf\r\nfrom tensorflow.python.keras import Model\r\nfrom tensorflow.python.keras.layers import Layer\r\n\r\n\r\nclass MyLayer(Layer):\r\n    def __init__(self, **kwargs):\r\n        super(MyLayer, self).__init__(**kwargs)\r\n\r\n    def call(self, input, training=None, mask=None):\r\n        self.add_metric(tf.ones([32]) * 2.0, name='two', aggregation='mean')\r\n        return input\r\n\r\n\r\nclass MyModel(Model):\r\n    def __init__(self, **kwargs):\r\n        super(MyModel, self).__init__(**kwargs)\r\n        self._sampler = MyLayer(name='sampler')\r\n\r\n    def call(self, input, training=None, mask=None):\r\n        z = self._sampler(input)\r\n        self.add_metric(tf.ones([32]) * 1.0, name='one', aggregation='mean')\r\n        self.add_metric(tf.ones([32]) * 3.0, name='three', aggregation='mean')\r\n        return z\r\n\r\n\r\ndef train(dataset_train, epochs):\r\n    tf.config.experimental_run_functions_eagerly(True)\r\n\r\n    optimizer = tf.keras.optimizers.Adam(learning_rate=1e-4)\r\n\r\n    loss = tf.losses.mean_squared_error\r\n\r\n    model = MyModel()\r\n    model.compile(optimizer=optimizer, loss=loss, run_eagerly=True)\r\n\r\n    print('Training...')\r\n    history = model.fit(dataset_train, epochs=epochs, verbose=1, callbacks=[])\r\n\r\n\r\ndef main():\r\n    print('Preparing data...')\r\n    batch_size = 32\r\n    num_examples = 32\r\n    xdata = np.random.uniform(size=[num_examples, 16]).astype(np.float32)\r\n    dataset_train = tf.data.Dataset.from_tensor_slices((xdata, xdata))\r\n    dataset_train = dataset_train.batch(batch_size, drop_remainder=True)\r\n\r\n    train(dataset_train, epochs=3)\r\n\r\n\r\nif __name__ == '__main__':\r\n    main()\r\n```\r\n\r\nOutput:\r\n```\r\n1/1 [==============================] - 0s 17ms/step - loss: 0.0000e+00 - two: 1.0000 - one: 3.0000 - three: 2.0000\r\n```\r\nNote how the values got mixed up. 'two' should assume a value of 2.0, 'one' a value of 1.0, 'three' a value of 3.0.\r\n\r\n**Other info / logs**\r\nThe problem appeared in a more complex example (training on GPU, graph mode), so although the minimal example above is using eager mode, it also happens when running non-eagerly.\r\n",
  "closed_by": {
    "login": "jvishnuvardhan",
    "id": 46058173,
    "node_id": "MDQ6VXNlcjQ2MDU4MTcz",
    "avatar_url": "https://avatars.githubusercontent.com/u/46058173?v=4",
    "gravatar_id": "",
    "url": "https://api.github.com/users/jvishnuvardhan",
    "html_url": "https://github.com/jvishnuvardhan",
    "followers_url": "https://api.github.com/users/jvishnuvardhan/followers",
    "following_url": "https://api.github.com/users/jvishnuvardhan/following{/other_user}",
    "gists_url": "https://api.github.com/users/jvishnuvardhan/gists{/gist_id}",
    "starred_url": "https://api.github.com/users/jvishnuvardhan/starred{/owner}{/repo}",
    "subscriptions_url": "https://api.github.com/users/jvishnuvardhan/subscriptions",
    "organizations_url": "https://api.github.com/users/jvishnuvardhan/orgs",
    "repos_url": "https://api.github.com/users/jvishnuvardhan/repos",
    "events_url": "https://api.github.com/users/jvishnuvardhan/events{/privacy}",
    "received_events_url": "https://api.github.com/users/jvishnuvardhan/received_events",
    "type": "User",
    "site_admin": false
  },
  "reactions": {
    "url": "https://api.github.com/repos/tensorflow/tensorflow/issues/32144/reactions",
    "total_count": 0,
    "+1": 0,
    "-1": 0,
    "laugh": 0,
    "hooray": 0,
    "confused": 0,
    "heart": 0,
    "rocket": 0,
    "eyes": 0
  },
  "timeline_url": "https://api.github.com/repos/tensorflow/tensorflow/issues/32144/timeline",
  "performed_via_github_app": null
}
